src/zmp_manual_chatbot_backend/__init__.py
src/zmp_manual_chatbot_backend/agents/__init__.py
src/zmp_manual_chatbot_backend/agents/anonymize_query_agent.py
src/zmp_manual_chatbot_backend/agents/answer_agent.py
src/zmp_manual_chatbot_backend/agents/base.py
src/zmp_manual_chatbot_backend/agents/break_down_plan_agent.py
src/zmp_manual_chatbot_backend/agents/de_anonymize_plan_agent.py
src/zmp_manual_chatbot_backend/agents/get_final_answer_agent.py
src/zmp_manual_chatbot_backend/agents/log_chat_history_agent.py
src/zmp_manual_chatbot_backend/agents/planner_agent.py
src/zmp_manual_chatbot_backend/agents/query_rewriter_agent.py
src/zmp_manual_chatbot_backend/agents/replan_agent.py
src/zmp_manual_chatbot_backend/agents/retrieve_context_agent.py
src/zmp_manual_chatbot_backend/agents/search_chat_history_agent.py
src/zmp_manual_chatbot_backend/agents/task_handler_agent.py
src/zmp_manual_chatbot_backend/agents.py
src/zmp_manual_chatbot_backend/config.py
src/zmp_manual_chatbot_backend/main.py
src/zmp_manual_chatbot_backend/mcp_client.py
src/zmp_manual_chatbot_backend/router.py
src/zmp_manual_chatbot_backend/schemas.py
src/zmp_manual_chatbot_backend/service.py
src/zmp_manual_chatbot_backend/session.py
src/zmp_manual_chatbot_backend/utils.py
src/zmp_manual_chatbot_backend/workflow_graph.png
zmp_manual_chatbot_backend-0.1.9.dist-info/LICENSE
zmp_manual_chatbot_backend-0.1.9.dist-info/METADATA
zmp_manual_chatbot_backend-0.1.9.dist-info/WHEEL
zmp_manual_chatbot_backend-0.1.9.dist-info/RECORD
