Metadata-Version: 2.3
Name: zmp-manual-chatbot-backend
Version: 0.1.9
Summary: Chatbot backend for ZMP Manual using FastAPI
Author: stiron
Author-email: lesch1@gmail.com
Requires-Python: >=3.12
Classifier: Programming Language :: Python :: 3
Classifier: Programming Language :: Python :: 3.12
Classifier: Programming Language :: Python :: 3.13
Requires-Dist: PyJWT (>=2.8.0,<3.0.0)
Requires-Dist: aiofiles (>=24.1.0,<25.0.0)
Requires-Dist: colorlog (>=6.9.0,<7.0.0)
Requires-Dist: fastapi (>=0.115.11,<0.116.0)
Requires-Dist: fastmcp (>=2.10.5,<3.0.0)
Requires-Dist: httpx (>=0.28.1,<0.29.0)
Requires-Dist: langchain (>=0.3.26,<0.4.0)
Requires-Dist: langchain-community (>=0.3.27,<0.4.0)
Requires-Dist: langchain-ollama (>=0.3.4,<0.4.0)
Requires-Dist: langchain-openai (>=0.3.28,<0.4.0)
Requires-Dist: langdetect (>=1.0.9,<2.0.0)
Requires-Dist: langgraph (>=0.5.2,<0.6.0)
Requires-Dist: openai (>=1.95.1,<2.0.0)
Requires-Dist: protobuf (>=6.31.1,<7.0.0)
Requires-Dist: pydantic-settings (>=2.10.1,<3.0.0)
Requires-Dist: pytest (>=8.4.1,<9.0.0)
Requires-Dist: python-dotenv (>=1.1.1,<2.0.0)
Requires-Dist: python-multipart (>=0.0.6,<1.0.0)
Requires-Dist: requests (>=2.31.0,<3.0.0)
Requires-Dist: starlette-csrf (>=3.0.0,<4.0.0)
Requires-Dist: uvicorn (>=0.35.0,<0.36.0)
Requires-Dist: zmp-authentication-provider (>=0.2.0,<0.3.0)
